bactfit/__init__.py
bactfit/cell.py
bactfit/fileIO.py
bactfit/fit.py
bactfit/postprocess.py
bactfit/preprocess.py
bactfit/utils.py
bactfit/dev/__init__.py
bactfit/dev/dev.py
bactfit/dev/example2.py
bactfit/dev/example_fit.py
bactfit/dev/localisations2.csv
bactfit/dev/mask.tif
bactfit/dev/mask2.tif
bactfit-0.1.6.dist-info/LICENSE
bactfit-0.1.6.dist-info/METADATA
bactfit-0.1.6.dist-info/WHEEL
bactfit-0.1.6.dist-info/top_level.txt
bactfit-0.1.6.dist-info/RECORD
