Metadata-Version: 2.1
Name: bactfit
Version: 0.1.6
Summary: Coordinate transformations for bacterial cell masks
Author: Piers Turner
Author-email: piers.turner@physics.ox.ac.uk
License: Copyright (c) 2024, Piers Turner
Project-URL: Source Code, https://github.com/piedrro/bactfit
Classifier: Development Status :: 2 - Pre-Alpha
Classifier: Intended Audience :: Developers
Classifier: License :: OSI Approved :: BSD License
Classifier: Operating System :: OS Independent
Classifier: Programming Language :: Python
Classifier: Programming Language :: Python :: 3
Classifier: Programming Language :: Python :: 3 :: Only
Classifier: Programming Language :: Python :: 3.9
Classifier: Programming Language :: Python :: 3.10
Classifier: Programming Language :: Python :: 3.11
Requires-Python: >=3.9
License-File: LICENSE
Requires-Dist: tifffile
Requires-Dist: numpy
Requires-Dist: opencv-python
Requires-Dist: matplotlib
Requires-Dist: scikit-image
Requires-Dist: scipy
Requires-Dist: shapely
Requires-Dist: tqdm
Requires-Dist: picassosr
Requires-Dist: glob2
